{"chunk_definitions":[{"chunk_id":"csetup_chunk","chunk_label":"setup","document_id":"BF4A165A","expansion_state":0,"options":{"engine":"r","include":false,"label":"setup"},"row":12,"row_count":1,"visible":true},{"chunk_id":"cl1onfji6nmm6","chunk_label":"unnamed-chunk-1","document_id":"BF4A165A","expansion_state":0,"options":{"engine":"r","include":false,"label":"unnamed-chunk-8"},"row":23,"row_count":1,"visible":true},{"chunk_id":"cpr64yeqgwzup","chunk_label":"unnamed-chunk-2","document_id":"BF4A165A","expansion_state":0,"options":{"engine":"r","include":false,"label":"unnamed-chunk-9"},"row":31,"row_count":1,"visible":true},{"chunk_id":"cg50r80rfrehk","chunk_label":"unnamed-chunk-3","document_id":"BF4A165A","expansion_state":0,"options":{"echo":false,"engine":"r","label":"unnamed-chunk-10"},"row":78,"row_count":1,"visible":true},{"chunk_id":"cnotanh0b1u15","chunk_label":"unnamed-chunk-4","document_id":"BF4A165A","expansion_state":0,"options":{"echo":false,"engine":"r","label":"unnamed-chunk-11","warning":false},"row":138,"row_count":1,"visible":true},{"chunk_id":"cx374951h5sle","chunk_label":"unnamed-chunk-5","document_id":"BF4A165A","expansion_state":0,"options":{"engine":"r","include":false,"label":"unnamed-chunk-50"},"row":185,"row_count":1,"visible":true},{"chunk_id":"c5pn47cc118bt","chunk_label":"unnamed-chunk-6","document_id":"BF4A165A","expansion_state":0,"options":{"echo":true,"engine":"r","label":"unnamed-chunk-13","tidy":true},"row":217,"row_count":1,"visible":true},{"chunk_id":"c5fv51vgl6ui9","chunk_label":"unnamed-chunk-7","document_id":"BF4A165A","expansion_state":0,"options":{"echo":false,"engine":"r","label":"unnamed-chunk-14"},"row":222,"row_count":1,"visible":true},{"chunk_id":"c3rhews3qmtbd","chunk_label":"unnamed-chunk-8","document_id":"BF4A165A","expansion_state":0,"options":{"echo":true,"engine":"r","label":"unnamed-chunk-53","warning":false},"row":233,"row_count":1,"visible":true}],"default_chunk_options":{"echo":true},"doc_write_time":1588043267,"working_dir":null}